stock_chart_tools/__init__.py
stock_chart_tools/utils.py
stock_chart_tools-0.1.0.dist-info/LICENSE
stock_chart_tools-0.1.0.dist-info/METADATA
stock_chart_tools-0.1.0.dist-info/WHEEL
stock_chart_tools-0.1.0.dist-info/top_level.txt
stock_chart_tools-0.1.0.dist-info/RECORD
